secret_2fa/__init__.py
secret_2fa/config.py
secret_2fa/document.py
secret_2fa/tags.py
secret_2fa-1.0.7.dist-info/LICENSE
secret_2fa-1.0.7.dist-info/METADATA
secret_2fa-1.0.7.dist-info/WHEEL
secret_2fa-1.0.7.dist-info/top_level.txt
secret_2fa-1.0.7.dist-info/RECORD
