Metadata-Version: 2.2
Name: secret_2fa
Version: 1.0.7
Summary: A Python library for handling secure 2fa authentication using Pyppeteer.
Author: Nguyễn Minh Đức
Author-email: Nguyễn Minh Đức <dancntt7@gmail.com>
License: MIT License
Requires-Python: >=3.10
License-File: LICENSE
Requires-Dist: pyppeteer
Dynamic: author
Dynamic: requires-python
